emrpy/__init__.py
emrpy/decorators.py
emrpy/py.typed
emrpy/really_utils.py
emrpy/telegrambot.py
emrpy/data/__init__.py
emrpy/data/loaders.py
emrpy/gcp/__init__.py
emrpy/logging/__init__.py
emrpy/logging/logger_config.py
emrpy/ml/__init__.py
emrpy/ml/encoders.py
emrpy/trading/__init__.py
emrpy/visualization/__init__.py
emrpy/visualization/finance.py
emrpy/visualization/timeseries.py
emr_py-0.6.0.dist-info/METADATA
emr_py-0.6.0.dist-info/WHEEL
emr_py-0.6.0.dist-info/licenses/LICENSE
emr_py-0.6.0.dist-info/RECORD
