Metadata-Version: 2.4
Name: emr-py
Version: 0.6.0
Summary: My custom library for data science, trading and ML projects
Author-email: Ezequiel Rivero <ezequielmrivero@gmail.com>
License-File: LICENSE
Requires-Python: <3.13,>=3.11
Requires-Dist: colorlog>=6.9.0
Requires-Dist: matplotlib>=3.10.3
Requires-Dist: numpy>=2.2.1
Requires-Dist: pandas>=2.2.3
Requires-Dist: polars>=1.30.0
Requires-Dist: pyarrow>=21.0.0
Requires-Dist: python-dotenv>=1.1.0
Requires-Dist: python-telegram-bot>=22.1
Requires-Dist: scikit-learn>=1.6.1
Requires-Dist: seaborn>=0.13.2
Provides-Extra: docs
Requires-Dist: sphinx-autobuild; extra == 'docs'
Requires-Dist: sphinx-autodoc-typehints; extra == 'docs'
Requires-Dist: sphinx-copybutton; extra == 'docs'
Requires-Dist: sphinx-rtd-theme; extra == 'docs'
Requires-Dist: sphinx>=7; extra == 'docs'
